{"unloaded_plugins": [], "plugins": ["wakatime/vim-wakatime", "styled-components/vim-styled-components", "posva/vim-vue", "vim-syntastic/syntastic", "mtscout6/syntastic-local-eslint.vim", "leafOfTree/vim-vue-plugin", "dart-lang/dart-vim-plugin", "thosakwe/vim-flutter", "joshdick/onedark.vim", "jwalton512/vim-blade", "wojciechkepka/vim-github-dark", "rescript-lang/vim-rescript", "github/copilot.vim", "nvim-tree/nvim-web-devicons", "lewis6991/gitsigns.nvim", "f-person/git-blame.nvim", "wuelnerdotexe/vim-astro", "prisma/vim-prisma", "mg979/vim-visual-multi", "marilari88/twoslash-queries.nvim", "voldikss/vim-floaterm"], "flags": {"format_on_save": true, "experimental_tsserver": true}, "bettervim_version": "3.15.0", "theme": "catppuccin-mocha", "lsps": ["bashls", "tsserver", "biome", "prismals", "astro", "tailwindcss"], "leader": ",", "distinct_id": "314df84e-dcdd-4c47-880c-33d516b56f1d", "treesitter": "all"}